{
  "__": {
    "width": 44,
    "height": 29,
    "x": 0,
    "y": 0,
    "pixelRatio": 2
  },
  "ad": {
    "width": 44,
    "height": 29,
    "x": 44,
    "y": 0,
    "pixelRatio": 2
  },
  "ae": {
    "width": 44,
    "height": 29,
    "x": 88,
    "y": 0,
    "pixelRatio": 2
  },
  "af": {
    "width": 44,
    "height": 29,
    "x": 132,
    "y": 0,
    "pixelRatio": 2
  },
  "ag": {
    "width": 44,
    "height": 29,
    "x": 176,
    "y": 0,
    "pixelRatio": 2
  },
  "ai": {
    "width": 44,
    "height": 29,
    "x": 220,
    "y": 0,
    "pixelRatio": 2
  },
  "al": {
    "width": 44,
    "height": 29,
    "x": 264,
    "y": 0,
    "pixelRatio": 2
  },
  "am": {
    "width": 44,
    "height": 29,
    "x": 308,
    "y": 0,
    "pixelRatio": 2
  },
  "ao": {
    "width": 44,
    "height": 29,
    "x": 352,
    "y": 0,
    "pixelRatio": 2
  },
  "aq": {
    "width": 44,
    "height": 29,
    "x": 396,
    "y": 0,
    "pixelRatio": 2
  },
  "ar": {
    "width": 44,
    "height": 29,
    "x": 440,
    "y": 0,
    "pixelRatio": 2
  },
  "as": {
    "width": 44,
    "height": 29,
    "x": 484,
    "y": 0,
    "pixelRatio": 2
  },
  "at": {
    "width": 44,
    "height": 29,
    "x": 528,
    "y": 0,
    "pixelRatio": 2
  },
  "au": {
    "width": 44,
    "height": 29,
    "x": 572,
    "y": 0,
    "pixelRatio": 2
  },
  "aw": {
    "width": 44,
    "height": 29,
    "x": 616,
    "y": 0,
    "pixelRatio": 2
  },
  "ax": {
    "width": 44,
    "height": 29,
    "x": 660,
    "y": 0,
    "pixelRatio": 2
  },
  "az": {
    "width": 44,
    "height": 29,
    "x": 704,
    "y": 0,
    "pixelRatio": 2
  },
  "ba": {
    "width": 44,
    "height": 29,
    "x": 748,
    "y": 0,
    "pixelRatio": 2
  },
  "bb": {
    "width": 44,
    "height": 29,
    "x": 792,
    "y": 0,
    "pixelRatio": 2
  },
  "bd": {
    "width": 44,
    "height": 29,
    "x": 836,
    "y": 0,
    "pixelRatio": 2
  },
  "be": {
    "width": 44,
    "height": 29,
    "x": 880,
    "y": 0,
    "pixelRatio": 2
  },
  "bf": {
    "width": 44,
    "height": 29,
    "x": 924,
    "y": 0,
    "pixelRatio": 2
  },
  "bg": {
    "width": 44,
    "height": 29,
    "x": 968,
    "y": 0,
    "pixelRatio": 2
  },
  "bh": {
    "width": 44,
    "height": 29,
    "x": 1012,
    "y": 0,
    "pixelRatio": 2
  },
  "bi": {
    "width": 44,
    "height": 29,
    "x": 1056,
    "y": 0,
    "pixelRatio": 2
  },
  "bj": {
    "width": 44,
    "height": 29,
    "x": 1100,
    "y": 0,
    "pixelRatio": 2
  },
  "bl": {
    "width": 44,
    "height": 29,
    "x": 1144,
    "y": 0,
    "pixelRatio": 2
  },
  "bm": {
    "width": 44,
    "height": 29,
    "x": 1188,
    "y": 0,
    "pixelRatio": 2
  },
  "bn": {
    "width": 44,
    "height": 29,
    "x": 1232,
    "y": 0,
    "pixelRatio": 2
  },
  "bo": {
    "width": 44,
    "height": 29,
    "x": 1276,
    "y": 0,
    "pixelRatio": 2
  },
  "bq": {
    "width": 44,
    "height": 29,
    "x": 1320,
    "y": 0,
    "pixelRatio": 2
  },
  "br": {
    "width": 44,
    "height": 29,
    "x": 1364,
    "y": 0,
    "pixelRatio": 2
  },
  "bs": {
    "width": 44,
    "height": 29,
    "x": 1408,
    "y": 0,
    "pixelRatio": 2
  },
  "bt": {
    "width": 44,
    "height": 29,
    "x": 1452,
    "y": 0,
    "pixelRatio": 2
  },
  "bv": {
    "width": 44,
    "height": 29,
    "x": 1496,
    "y": 0,
    "pixelRatio": 2
  },
  "bw": {
    "width": 44,
    "height": 29,
    "x": 1540,
    "y": 0,
    "pixelRatio": 2
  },
  "by": {
    "width": 44,
    "height": 29,
    "x": 1584,
    "y": 0,
    "pixelRatio": 2
  },
  "bz": {
    "width": 44,
    "height": 29,
    "x": 1628,
    "y": 0,
    "pixelRatio": 2
  },
  "ca": {
    "width": 44,
    "height": 29,
    "x": 1672,
    "y": 0,
    "pixelRatio": 2
  },
  "cc": {
    "width": 44,
    "height": 29,
    "x": 1716,
    "y": 0,
    "pixelRatio": 2
  },
  "cd": {
    "width": 44,
    "height": 29,
    "x": 1760,
    "y": 0,
    "pixelRatio": 2
  },
  "cf": {
    "width": 44,
    "height": 29,
    "x": 1804,
    "y": 0,
    "pixelRatio": 2
  },
  "cg": {
    "width": 44,
    "height": 29,
    "x": 1848,
    "y": 0,
    "pixelRatio": 2
  },
  "ch": {
    "width": 44,
    "height": 29,
    "x": 1892,
    "y": 0,
    "pixelRatio": 2
  },
  "ci": {
    "width": 44,
    "height": 29,
    "x": 1936,
    "y": 0,
    "pixelRatio": 2
  },
  "ck": {
    "width": 44,
    "height": 29,
    "x": 1980,
    "y": 0,
    "pixelRatio": 2
  },
  "cl": {
    "width": 44,
    "height": 29,
    "x": 2024,
    "y": 0,
    "pixelRatio": 2
  },
  "cm": {
    "width": 44,
    "height": 29,
    "x": 2068,
    "y": 0,
    "pixelRatio": 2
  },
  "cn": {
    "width": 44,
    "height": 29,
    "x": 2112,
    "y": 0,
    "pixelRatio": 2
  },
  "co": {
    "width": 44,
    "height": 29,
    "x": 2156,
    "y": 0,
    "pixelRatio": 2
  }
}